README.md
setup.py
mob_scrapy_redis_sentinel/__init__.py
mob_scrapy_redis_sentinel/bloomfilter.py
mob_scrapy_redis_sentinel/connection.py
mob_scrapy_redis_sentinel/defaults.py
mob_scrapy_redis_sentinel/dupefilter.py
mob_scrapy_redis_sentinel/picklecompat.py
mob_scrapy_redis_sentinel/pipelines.py
mob_scrapy_redis_sentinel/queue.py
mob_scrapy_redis_sentinel/scheduler.py
mob_scrapy_redis_sentinel/spiders.py
mob_scrapy_redis_sentinel/stats.py
mob_scrapy_redis_sentinel/utils.py
mob_scrapy_redis_sentinel.egg-info/PKG-INFO
mob_scrapy_redis_sentinel.egg-info/SOURCES.txt
mob_scrapy_redis_sentinel.egg-info/dependency_links.txt
mob_scrapy_redis_sentinel.egg-info/not-zip-safe
mob_scrapy_redis_sentinel.egg-info/requires.txt
mob_scrapy_redis_sentinel.egg-info/top_level.txt