Metadata-Version: 2.1
Name: mob-scrapy-redis-sentinel
Version: 0.5
Summary: Redis Cluster for Scrapy.
Home-page: https://github.com/crawlmap/scrapy-redis-sentinel.git
Author: luzihang
Author-email: luzhang@mob.com
License: MIT
Project-URL: Documentation, https://crawlaio.com/scrapy-redis-sentinel/
Keywords: scrapy-redis,scrapy-redis-sentinel,scrapy-redis-cluster
Platform: UNKNOWN
Classifier: License :: OSI Approved :: MIT License
Classifier: Programming Language :: Python :: 3.6
Classifier: Programming Language :: Python :: 3.7
Classifier: Programming Language :: Python :: 3.8
Classifier: Programming Language :: Python :: 3.9
